{
  "name" : "data1",
  "value" : 9,
  "children" : [
    {
      "name" : "analytics",
      "value" : 2,
      "children" : null
    },
    {
      "name" : "graph",
      "value" : 3,
      "children" : [
        {
          "name" : "betweenness",
          "value" : 1,
          "children" : null
        },
        {
          "name" : "centrality",
          "value" : 1,
          "children" : null
        },
        {
          "name" : "degree",
          "value" : 1,
          "children" : null
        }
      ]
    },
    {
      "name" : "optimization",
      "value" : 4,
      "children" : [
        {
          "name" : "convex",
          "value" : 1,
          "children" : null
        },
        {
          "name" : "gradient",
          "value" : 1,
          "children" : null
        },
        {
          "name" : "linear",
          "value" : 1,
          "children" : null
        },
        {
          "name" : "nonlinear",
          "value" : 1,
          "children" : null
        }
      ]
    }
  ]
}
  